CoastalFSM.v
// Modul FSM untuk Coastal Wave Impact Predictor
module CoastalFSM (
    input clk,          // Clock
    input reset,        // Sinyal reset asinkron
    input X,            // Input X (Risiko Apapun = H+F+T+I+R+D)
    input C_Total,      // Input C_Total (Krisis Total = H.F.T.I.R.D)
    
    // Output FSM (Status Aktuator yang Dikelompokkan)
    output reg O_Kritis,      // Output untuk Krisis (Buzzer, dll.)
    output reg O_Investigasi  // Output untuk Investigasi (MA, FW, SHT)
);

// Definisi state menggunakan parameter
parameter S0_AMAN     = 2'b00;  // NORMAL
parameter S1_WASPADA  = 2'b01;  // PERINGATAN
parameter S2_BAHAYA   = 2'b10;  // KRISIS TOTAL

reg [1:0] current_state;
reg [1:0] next_state;

// Logika Sekuensial: Pembaruan state
always @(posedge clk or posedge reset) begin
    if (reset)
        current_state <= S0_AMAN;
    else
        current_state <= next_state;
end

// Logika Kombinasional: Tabel Transisi Status (Step 3 yang dikoreksi)
always @(*) begin
    next_state = current_state; // Default: Tetap di state saat ini
    
    case (current_state)
        S0_AMAN: begin
            if (C_Total) next_state = S2_BAHAYA; // 00 -> 10 (Krisis)
            else if (X)   next_state = S1_WASPADA; // 00 -> 01 (Peringatan)
        end
        
        S1_WASPADA: begin
            if (C_Total) next_state = S2_BAHAYA; // 01 -> 10 (Krisis)
            else if (!X) next_state = S0_AMAN;   // 01 -> 00 (Kembali Normal)
            // else jika X=1 & C_Total=0, tetap di S1_WASPADA
        end
        
        S2_BAHAYA: begin
            if (!X) next_state = S0_AMAN; // 10 -> 00 (Kembali Normal)
            else if (!C_Total) next_state = S1_WASPADA; // 10 -> 01 (Krisis Mereda)
            // else jika X=1 & C_Total=1, tetap di S2_BAHAYA
        end
        
        default: next_state = S0_AMAN;
    endcase
end

// Logika Output: Berdasarkan Status Saat Ini (Moore Machine)
always @(current_state) begin
    O_Kritis = 0;
    O_Investigasi = 0;

    case (current_state)
        S0_AMAN: begin
            O_Kritis = 0;
            O_Investigasi = 0;
        end
        S1_WASPADA: begin
            O_Kritis = 0;
            O_Investigasi = 1; // Aktifkan MA, FW, SHT
        end
        S2_BAHAYA: begin
            O_Kritis = 1;      // Aktifkan Buzzer
            O_Investigasi = 1; // Aktifkan MA, FW, SHT
        end
        default: begin
            O_Kritis = 0;
            O_Investigasi = 0;
        end
    endcase
end

endmodule

CoastalFSM_tb.v
`timescale 1ns / 1ps

module CoastalFSM_tb;

    // Deklarasi Sinyal (Wires/Regs) yang menghubungkan ke modul FSM
    reg clk;
    reg reset;
    reg X;          // Input Risiko Apapun (X = H+F+T+I+R+D)
    reg C_Total;    // Input Krisis Total (C_Total = H.F.T.I.R.D)
    
    wire O_Kritis;
    wire O_Investigasi;

    // Inisialisasi parameter Waktu
    parameter CLK_PERIOD = 10; // Periode clock = 10ns (Frekuensi 100MHz)

    // 1. Instansiasi Modul Desain (UUT: Unit Under Test)
    CoastalFSM UUT (
        .clk(clk),
        .reset(reset),
        .X(X),
        .C_Total(C_Total),
        .O_Kritis(O_Kritis),
        .O_Investigasi(O_Investigasi)
    );

    // 2. Clock Generation
    // Hasilkan sinyal clock dengan duty cycle 50%
    initial begin
        clk = 0;
        forever #(CLK_PERIOD/2) clk = ~clk; 
    end

    // 3. Stimulus Generation (Sekuens Uji)
    initial begin
        // Inisialisasi Awal
        reset = 1;
        X = 0;
        C_Total = 0;
        
        // Mulai Dumpsing VCD (untuk visualisasi waveform)
        $dumpfile("CoastalFSM_tb.vcd");
        $dumpvars(0, CoastalFSM_tb); 

        // Tahan reset selama 20 ns
        #(2*CLK_PERIOD) reset = 0; 
        
        // Uji Skenario Transisi

        // --- Skenario 1: S0 (NORMAL) -> S1 (WASPADA) -> S0 (NORMAL)
        #(CLK_PERIOD); // Tunggu stabil di S0
        $display("Time %0t: S0 -> S1 (Peringatan Awal)", $time);
        X = 1; C_Total = 0; // Risiko Terdeteksi, Bukan Krisis
        
        #(5*CLK_PERIOD); 
        $display("Time %0t: S1 -> S0 (Kembali Normal)", $time);
        X = 0; C_Total = 0; // Risiko Hilang
        
        // --- Skenario 2: S0 (NORMAL) -> S2 (KRISIS TOTAL)
        #(5*CLK_PERIOD); 
        $display("Time %0t: S0 -> S2 (Krisis Penuh)", $time);
        X = 1; C_Total = 1; // Semua Risiko Kritis ON
        
        // --- Skenario 3: S2 (KRISIS TOTAL) -> S1 (KRISIS MEREDA)
        #(5*CLK_PERIOD); 
        $display("Time %0t: S2 -> S1 (Krisis Mereda)", $time);
        X = 1; C_Total = 0; // Risiko Masih Ada (X=1) tapi Krisis Total OFF (C_Total=0)

        // --- Skenario 4: S1 (WASPADA) -> S2 (KRISIS)
        #(5*CLK_PERIOD); 
        $display("Time %0t: S1 -> S2 (Krisis Kembali)", $time);
        X = 1; C_Total = 1; // Kembali ke Krisis Total

        // --- Skenario 5: S2 (KRISIS) -> S0 (RESET PENUH)
        #(5*CLK_PERIOD);
        $display("Time %0t: S2 -> S0 (Emergency Reset)", $time);
        X = 0; C_Total = 0; // Semua Risiko Mati

        // Akhiri Simulasi
        #(10*CLK_PERIOD) $finish;
    end

endmodule

CoastalFSM_tb.vcd
$date
	Mon Dec 08 03:24:32 2025
$end
$version
	Icarus Verilog
$end
$timescale
	1ps
$end
$scope module CoastalFSM_tb $end
$var wire 1 ! O_Kritis $end
$var wire 1 " O_Investigasi $end
$var reg 1 # C_Total $end
$var reg 1 $ X $end
$var reg 1 % clk $end
$var reg 1 & reset $end
$scope module UUT $end
$var wire 1 # C_Total $end
$var wire 1 $ X $end
$var wire 1 % clk $end
$var wire 1 & reset $end
$var reg 1 " O_Investigasi $end
$var reg 1 ! O_Kritis $end
$var reg 2 ' current_state [1:0] $end
$var reg 2 ( next_state [1:0] $end
$upscope $end
$upscope $end
$enddefinitions $end
#0
$dumpvars
b0 (
b0 '
1&
0%
0$
0#
0"
0!
$end
#5000
1%
#10000
0%
#15000
1%
#20000
0%
0&
#25000
1%
#30000
b1 (
0%
1$
#35000
1"
b1 '
1%
#40000
0%
#45000
1%
#50000
0%
#55000
1%
#60000
0%
#65000
1%
#70000
0%
#75000
1%
#80000
b0 (
0%
0$
#85000
0"
b0 '
1%
#90000
0%
#95000
1%
#100000
0%
#105000
1%
#110000
0%
#115000
1%
#120000
0%
#125000
1%
#130000
b10 (
0%
1#
1$
#135000
1"
1!
b10 '
1%
#140000
0%
#145000
1%
#150000
0%
#155000
1%
#160000
0%
#165000
1%
#170000
0%
#175000
1%
#180000
b1 (
0%
0#
#185000
1"
0!
b1 '
1%
#190000
0%
#195000
1%
#200000
0%
#205000
1%
#210000
0%
#215000
1%
#220000
0%
#225000
1%
#230000
b10 (
0%
1#
#235000
1!
1"
b10 '
1%
#240000
0%
#245000
1%
#250000
0%
#255000
1%
#260000
0%
#265000
1%
#270000
0%
#275000
1%
#280000
b0 (
0%
0#
0$
#285000
0"
0!
b0 '
1%
